{
  "name": "combat-animator",
  "title": "Combat Animator - Add flashy animations to combat",
  "description": "A module to make VTT more interesting to watch",
  "author": "Euno",
  "version": "0.0.1",
  "minimumCoreVersion": "0.7.5",
  "compatibleCoreVersion": "0.7.5",
  "url": "https://github.com/EunoTheBard/combat_animator",
  "scripts": [
    "scripts/roller.js"
  ],
  "manifest": "https://raw.githubusercontent.com/EunoTheBard/combat_animator/main/module.json",
  "download": "https://github.com/EunoTheBard/combat_animator/archive/0.0.2.zip"
}
